timegraph/__init__.py
timegraph/abstime.py
timegraph/constants.py
timegraph/pred.py
timegraph/timegraph.py
timegraph/timestructs.py
timegraph/util.py
timegraph-0.0.7.dist-info/METADATA
timegraph-0.0.7.dist-info/WHEEL
timegraph-0.0.7.dist-info/licenses/LICENSE
timegraph-0.0.7.dist-info/RECORD
