Metadata-Version: 2.1
Name: timegraph
Version: 0.0.7
Summary: An implementation of the timegraph data structure and algorithm for evaluating temporal relations.
Project-URL: Homepage, https://github.com/bkane2/timegraph-py
Project-URL: Bug Tracker, https://github.com/bkane2/timegraph-py/issues
Author-email: Benjamin Kane <Ben.Kane@me.com>
License-File: LICENSE
Classifier: License :: OSI Approved :: MIT License
Classifier: Operating System :: OS Independent
Classifier: Programming Language :: Python :: 3
Requires-Python: >=3.7
Requires-Dist: graphviz
